cometx/__init__.py
cometx/_typing.py
cometx/_ui.py
cometx/_version.py
cometx/api.py
cometx/audio.py
cometx/generate_utils.py
cometx/magics.py
cometx/optimizer.py
cometx/panel_utils.py
cometx/utils.py
cometx/cli/__init__.py
cometx/cli/admin.py
cometx/cli/config.py
cometx/cli/copy.py
cometx/cli/copy_utils.py
cometx/cli/count.py
cometx/cli/delete_assets.py
cometx/cli/download.py
cometx/cli/list_command.py
cometx/cli/log.py
cometx/cli/reproduce.py
cometx/cli/smoke_test.py
cometx/cli/update.py
cometx/cli/utils.py
cometx/framework/__init__.py
cometx/framework/wandb.py
cometx/framework/comet/__init__.py
cometx/framework/comet/download_manager.py
cometx/tools/__init__.py
cometx/tools/dataset.py
cometx/tools/pointcloud.py
cometx-3.1.0.dist-info/licenses/LICENSE
cometx-3.1.0.dist-info/METADATA
cometx-3.1.0.dist-info/WHEEL
cometx-3.1.0.dist-info/entry_points.txt
cometx-3.1.0.dist-info/top_level.txt
cometx-3.1.0.dist-info/RECORD
