Metadata-Version: 2.4
Name: cometx
Version: 3.1.0
Summary: Python tools for Comet
Home-page: https://github.com/comet-ml/cometx/
Author: cometx development team
License: MIT License
Keywords: ai,artificial intelligence,python,machine learning
Platform: Linux
Platform: Mac OS X
Platform: Windows
Classifier: License :: OSI Approved :: MIT License
Classifier: Programming Language :: Python
Classifier: Programming Language :: Python :: 3
Classifier: Programming Language :: Python :: 3.6
Classifier: Programming Language :: Python :: 3.7
Classifier: Programming Language :: Python :: 3.8
Classifier: Programming Language :: Python :: 3.9
Classifier: Framework :: Jupyter
Requires-Python: >=3.6
License-File: LICENSE
Requires-Dist: comet_ml>=3.49.1
Requires-Dist: rich>=13.0.0
Requires-Dist: six
Requires-Dist: requests
Requires-Dist: tqdm
Provides-Extra: all
Requires-Dist: pillow>=11.1.0; extra == "all"
Requires-Dist: opik; extra == "all"
Requires-Dist: comet_mpm; extra == "all"
Requires-Dist: numpy; extra == "all"
Requires-Dist: scikit-learn; extra == "all"
Requires-Dist: matplotlib; extra == "all"
Requires-Dist: scipy; extra == "all"
Requires-Dist: ipywidgets; extra == "all"
Requires-Dist: markdown; extra == "all"
Requires-Dist: IPython; extra == "all"
Requires-Dist: wandb; extra == "all"
Dynamic: author
Dynamic: classifier
Dynamic: description
Dynamic: description-content-type
Dynamic: home-page
Dynamic: keywords
Dynamic: license
Dynamic: license-file
Dynamic: platform
Dynamic: provides-extra
Dynamic: requires-dist
Dynamic: requires-python
Dynamic: summary
